agentwf/__init__.py
agentwf/core.py
agentwf-0.1.0.dist-info/METADATA
agentwf-0.1.0.dist-info/WHEEL
agentwf-0.1.0.dist-info/top_level.txt
agentwf-0.1.0.dist-info/RECORD
